{
  "version": 1,
  "zones": [
    {
      "id": "hula-valley",
      "name": "עמק החולה",
      "polygon": [[35.55, 33.15], [35.65, 33.15], [35.65, 33.22], [35.55, 33.22], [35.55, 33.15]]
    },
    {
      "id": "galilee-panhandle",
      "name": "אצבע הגליל",
      "polygon": [[35.55, 33.22], [35.65, 33.22], [35.65, 33.30], [35.55, 33.30], [35.55, 33.22]]
    },
    {
      "id": "dafna-cluster",
      "name": "דפנה והגושרים",
      "polygon": [[35.60, 33.20], [35.70, 33.20], [35.70, 33.26], [35.60, 33.26], [35.60, 33.20]]
    },
    {
      "id": "north-golan",
      "name": "צפון הגולן",
      "polygon": [[35.65, 33.18], [35.80, 33.18], [35.80, 33.30], [35.65, 33.30], [35.65, 33.18]]
    },
    {
      "id": "south-golan",
      "name": "דרום הגולן",
      "polygon": [[35.65, 33.05], [35.85, 33.05], [35.85, 33.18], [35.65, 33.18], [35.65, 33.05]]
    }
  ]
}
